gritscope/py.typed
gritscope/plot/graphplot.toml
gritscope/plot/vegaplot.py
gritscope/powergrid/fdpf.py
gritscope/powergrid/flow.py
gritscope/powergrid/grid.py
gritscope/powergrid/metrics.py
gritscope/powergrid/pandapower.py
gritscope/powergrid/plot.py
gritscope/powergrid/protocol.py
gritscope/search/gritscope.select.py
gritscope/search/metrics.py
gritscope/topology/abc.py
gritscope/topology/coords.py
gritscope/topology/graphs.py
gritscope/topology/guards.py
gritscope/topology/itertools.py
gritscope/topology/spaces.py
gritscope-0.4.1.dist-info/LICENSE
gritscope-0.4.1.dist-info/METADATA
gritscope-0.4.1.dist-info/WHEEL
gritscope-0.4.1.dist-info/top_level.txt
gritscope-0.4.1.dist-info/RECORD
